rytr/__init__.py
rytr/content.py
rytr/helpers.py
rytr/languages.py
rytr/tones.py
rytr/usecases.py
rytr-0.0.3.dist-info/LICENSE
rytr-0.0.3.dist-info/METADATA
rytr-0.0.3.dist-info/WHEEL
rytr-0.0.3.dist-info/top_level.txt
rytr-0.0.3.dist-info/RECORD
