Metadata-Version: 2.1
Name: rytr
Version: 0.0.3
Summary: Python package for RYTR
Home-page: https://marcosaguayo.com/
Download-URL: https://github.com/maguayo/rytr-python
Author: MarcosAguayo
Author-email: marcos@aguayo.es
License: GPL-3
Classifier: Environment :: Web Environment
Classifier: Intended Audience :: Developers
Classifier: License :: OSI Approved :: GNU Affero General Public License v3
Classifier: Operating System :: OS Independent
Classifier: Programming Language :: Python
Classifier: Topic :: Internet :: WWW/HTTP :: Dynamic Content
Classifier: Topic :: Software Development :: Libraries :: Python Modules
License-File: LICENSE
